promptly/__init__.py
promptly/py.typed
promptly/cli/__init__.py
promptly/cli/main.py
promptly/core/__init__.py
promptly/core/client_types.py
promptly/core/clients.py
promptly/core/optimizer.py
promptly/core/runner.py
promptly/core/templates.py
promptly/core/tracer.py
promptly/core/utils/ai.py
promptly/core/utils/env.py
promptly_llm-0.2.0.dist-info/licenses/LICENSE
promptly_llm-0.2.0.dist-info/METADATA
promptly_llm-0.2.0.dist-info/WHEEL
promptly_llm-0.2.0.dist-info/entry_points.txt
promptly_llm-0.2.0.dist-info/top_level.txt
promptly_llm-0.2.0.dist-info/RECORD
