Metadata-Version: 2.4
Name: promptly-llm
Version: 0.2.0
Summary: A lightweight library for LLM prompt management, observability/tracing, and optimization
Author-email: Tucker Leach <leachtucker@gmail.com>
License-Expression: MIT
Project-URL: Homepage, https://github.com/orgpromptly/promptly
Project-URL: Documentation, https://github.com/orgpromptly/promptly#readme
Project-URL: Repository, https://github.com/orgpromptly/promptly
Project-URL: Issues, https://github.com/orgpromptly/promptly/issues
Project-URL: Changelog, https://github.com/orgpromptly/promptly/blob/main/CHANGELOG.md
Keywords: llm,prompt,ai,machine-learning,evaluation
Classifier: Development Status :: 3 - Alpha
Classifier: Intended Audience :: Developers
Classifier: Programming Language :: Python :: 3.9
Classifier: Programming Language :: Python :: 3.10
Classifier: Programming Language :: Python :: 3.11
Classifier: Programming Language :: Python :: 3.12
Classifier: Programming Language :: Python :: 3.13
Requires-Python: >=3.9
License-File: LICENSE
Requires-Dist: jinja2>=3.0.0
Requires-Dist: openai>=1.0.0
Requires-Dist: anthropic>=0.18.0
Requires-Dist: google-genai>=1.46.0
Requires-Dist: pydantic>=2.0.0
Requires-Dist: aiohttp>=3.8.0
Requires-Dist: python-dotenv>=1.0.0
Provides-Extra: dev
Requires-Dist: pytest>=7.0.0; extra == "dev"
Requires-Dist: pytest-asyncio>=0.21.0; extra == "dev"
Requires-Dist: pytest-cov>=4.0.0; extra == "dev"
Requires-Dist: ruff>=0.1.0; extra == "dev"
Requires-Dist: pyright>=1.1.0; extra == "dev"
Requires-Dist: commitizen>=3.0.0; extra == "dev"
Requires-Dist: pre-commit>=3.0.0; extra == "dev"
Requires-Dist: twine>=4.0.0; extra == "dev"
Provides-Extra: cli
Requires-Dist: click>=8.0.0; extra == "cli"
Requires-Dist: rich>=13.0.0; extra == "cli"
Provides-Extra: ui
Requires-Dist: fastapi>=0.100.0; extra == "ui"
Requires-Dist: uvicorn>=0.20.0; extra == "ui"
Requires-Dist: streamlit>=1.20.0; extra == "ui"
Dynamic: license-file
